helipad/Helipad.png
helipad/__init__.py
helipad/agent.py
helipad/cpanelJupyter.py
helipad/cpanelTkinter.py
helipad/data.py
helipad/helpers.py
helipad/ipy-styles.css
helipad/model.py
helipad/param.py
helipad/spatial.py
helipad/utility.py
helipad/visualize.py
helipad/locales/helipad.pot
helipad/locales/en/LC_MESSAGES/helipad.mo
helipad-1.6.3.dist-info/licenses/LICENSE
sample-models/Cities.py
sample-models/Helicopter-OMO.py
sample-models/Helicopter.py
sample-models/axelrod.py
sample-models/bootstrap.py
sample-models/cpanel-test.py
sample-models/crime.py
sample-models/criticalperiod.py
sample-models/demeSelection.py
sample-models/gameoflife.py
sample-models/grass.py
sample-models/pricediscover.py
sample-models/prisoners.py
sample-notebooks/axelrod.ipynb
sample-notebooks/cpanel-test.ipynb
sample-notebooks/helicopter.ipynb
sample-notebooks/pricediscover.ipynb
sample-notebooks/viz-tutorial.ipynb
helipad-1.6.3.dist-info/METADATA
helipad-1.6.3.dist-info/WHEEL
helipad-1.6.3.dist-info/top_level.txt
helipad-1.6.3.dist-info/RECORD
