Metadata-Version: 2.4
Name: helipad
Version: 1.6.3
Summary: An agent-based modeling framework for Python with a shallow learning curve and powerful visualization capabilities.
Author-email: C Harwick <cameron@cameronharwick.com>
License: MIT License
Project-URL: Homepage, https://helipad.dev
Project-URL: Documentation, https://helipad.dev/functions/
Project-URL: Source Code, https://github.com/charwick/helipad
Classifier: Programming Language :: Python :: 3
Classifier: License :: OSI Approved :: MIT License
Classifier: Operating System :: OS Independent
Classifier: Development Status :: 5 - Production/Stable
Classifier: Intended Audience :: Science/Research
Classifier: Topic :: Scientific/Engineering :: Visualization
Requires-Python: >=3.10
License-File: LICENSE
Requires-Dist: matplotlib
Requires-Dist: pandas
Requires-Dist: networkx
Provides-Extra: notebook
Requires-Dist: jupyterlab; extra == "notebook"
Requires-Dist: ipywidgets>=8.0; extra == "notebook"
Requires-Dist: ipympl; extra == "notebook"
Provides-Extra: geo
Requires-Dist: shapely; extra == "geo"
Dynamic: license-file
